{
    "category": [
        "Invertebrate"
    ],
    "taxon_group": [
        "insect - true bug (Hemiptera)"
    ],
    "recommended_taxon_name": [
        "Hesperocorixa castanea"
    ],
    "recommended_authority": [
        "(Thomson, 1869)"
    ],
    "recommended_qualifier": [
        null
    ],
    "recommended_taxon_version": [
        "NHMSYS0000527543"
    ],
    "designations": [
        {
            "designated_name": "Hesperocorixa castanea",
            "source": "A review of the Hemiptera of Great Britain: The Aquatic and Semi-aquatic Bugs",
            "source_description": "This report was commissioned to update the national status of aquatic and semi-aquatic bugs using IUCN methodology for assessing threat. It covers all species of aquatic and semi-aquatic bugs (Heteroptera) in Great Britain, identifying those that are rare and/or under threat as well as non-threatened and non-native species. A.A. Cook November 2015.",
            "url_source": "http://publications.naturalengland.org.uk/publication/5132432324952064",
            "date_designated": "2015-11-20",
            "reporting_category": "Red listing based on 2001 IUCN guidelines",
            "designation": "Least concern",
            "designation_abbreviation": "RedList_GB_post2001-LC",
            "designation_description": "Taxa which are neither threatened nor near threatened.",
            "iucn_version": "2001",
            "reporting_category_sort_order": "Fc"
        }
    ]
}

